botdash/Client.py
botdash/__init__.py
botdash/lib/__init__.py
botdash/lib/value.py
botdash.py-0.0.5.dist-info/LICENSE
botdash.py-0.0.5.dist-info/METADATA
botdash.py-0.0.5.dist-info/WHEEL
botdash.py-0.0.5.dist-info/top_level.txt
botdash.py-0.0.5.dist-info/RECORD
