Metadata-Version: 2.1
Name: botdash.py
Version: 0.0.5
Summary: API wrapper for botdash.pro
Home-page: https://github.com/jetnox/botdash-py
Author: Jetnox
Author-email: seer@jetblaze.org
License: MIT
Download-URL: https://github.com/jetnox/botdash-py/tarball/master
Keywords: botdash,discord,bot
Platform: UNKNOWN
License-File: LICENSE
Requires-Dist: setuptools
Requires-Dist: requests
Requires-Dist: six
Requires-Dist: ujson
